odooquery/__init__.py
odooquery/mass_mailing.py
odooquery/messages.py
odooquery/order.py
odooquery/partner.py
odooquery/products.py
odooquery/query.py
odooquery/ticket.py
odooquery/types.py
odooquery/utils/__init__.py
odooquery/utils/text_processing.py
odooquery-0.1.0.post28.dist-info/METADATA
odooquery-0.1.0.post28.dist-info/WHEEL
odooquery-0.1.0.post28.dist-info/licenses/LICENSE
odooquery-0.1.0.post28.dist-info/RECORD
