Metadata-Version: 2.4
Name: odooquery
Version: 0.1.0.post28
Summary: A library to add specific query functionality on top of odoorpc for higher-level functions
Project-URL: Repository, https://github.com/benagricola/odooquery
Project-URL: Documentation, https://github.com/benagricola/odooquery#readme
Author-email: Ben Agricola <odooquery@lawlr.us>
License: MIT
License-File: LICENSE
Classifier: Development Status :: 3 - Alpha
Classifier: Intended Audience :: Developers
Classifier: Programming Language :: Python :: 3.12
Requires-Python: >=3.12
Requires-Dist: beautifulsoup4>=4.13.3
Requires-Dist: odoorpc>=0.10.1
Requires-Dist: pydantic>=2.10.6
Requires-Dist: typing-extensions>=4.12.2
